Metadata-Version: 2.1
Name: SimplifiedCGE_CHN_0.2
Version: 0.2
Summary: This model is a simplified version of a CGE model for China, including 2-factor inputs, 3 sectors, 2 final consumers, investment and saving account.
Home-page: https://junexqu.github.io/
Author: Junxi Qu (HKU)
Author-email: qujunxi@connect.hku.hk
Classifier: Programming Language :: Python :: 3
Classifier: License :: OSI Approved :: MIT License
Requires-Python: >=3.6
Requires-Dist: numpy
Requires-Dist: pandas
Requires-Dist: scipy
